mindinsight/__init__.py
mindinsight/__main__.py
mindinsight/_version.py
mindinsight/backend/__init__.py
mindinsight/backend/application.py
mindinsight/backend/run.py
mindinsight/backend/config/__init__.py
mindinsight/backend/config/gunicorn_conf.py
mindinsight/backend/data_manager/__init__.py
mindinsight/backend/datavisual/__init__.py
mindinsight/backend/datavisual/static_resource_api.py
mindinsight/backend/datavisual/task_manager_api.py
mindinsight/backend/datavisual/train_visual_api.py
mindinsight/backend/debugger/__init__.py
mindinsight/backend/debugger/debugger_api.py
mindinsight/backend/explainer/__init__.py
mindinsight/backend/explainer/explainer_api.py
mindinsight/backend/lineagemgr/__init__.py
mindinsight/backend/lineagemgr/lineage_api.py
mindinsight/backend/optimizer/__init__.py
mindinsight/backend/optimizer/optimizer_api.py
mindinsight/backend/profiler/__init__.py
mindinsight/backend/profiler/marey_graph_api.py
mindinsight/backend/profiler/parallel_strategy_api.py
mindinsight/backend/profiler/profile_api.py
mindinsight/backend/ui_config/__init__.py
mindinsight/backend/ui_config/ui_config_api.py
mindinsight/common/__init__.py
mindinsight/common/util.py
mindinsight/common/hook/__init__.py
mindinsight/common/hook/datavisual.py
mindinsight/common/hook/debugger.py
mindinsight/conf/__init__.py
mindinsight/conf/constants.py
mindinsight/conf/defaults.py
mindinsight/datavisual/__init__.py
mindinsight/datavisual/common/__init__.py
mindinsight/datavisual/common/enums.py
mindinsight/datavisual/common/error_handler.py
mindinsight/datavisual/common/exceptions.py
mindinsight/datavisual/common/log.py
mindinsight/datavisual/common/validation.py
mindinsight/datavisual/data_access/__init__.py
mindinsight/datavisual/data_access/base_file_system.py
mindinsight/datavisual/data_access/file_handler.py
mindinsight/datavisual/data_access/local_file_system.py
mindinsight/datavisual/data_transform/__init__.py
mindinsight/datavisual/data_transform/data_loader.py
mindinsight-2.3.1.dist-info/LICENSE
mindinsight-2.3.1.dist-info/METADATA
mindinsight-2.3.1.dist-info/NOTICE
mindinsight-2.3.1.dist-info/WHEEL
mindinsight-2.3.1.dist-info/entry_points.txt
mindinsight-2.3.1.dist-info/top_level.txt
mindinsight-2.3.1.dist-info/RECORD
