Metadata-Version: 2.1
Name: mindinsight
Version: 2.3.1
Summary: mindinsight platform: linux, cpu: x86_64, git version: [sha1]:6e8f0e75, [branch]: (HEAD -> master, origin/master, origin/HEAD)
Home-page: https://www.mindspore.cn
Download-URL: https://gitee.com/mindspore/mindinsight/tags
Author: The MindSpore Authors
Author-email: contact@mindspore.cn
License: Apache 2.0
Project-URL: Sources, https://gitee.com/mindspore/mindinsight
Project-URL: Issue Tracker, https://gitee.com/mindspore/mindinsight/issues
Keywords: mindinsight
Platform: linux
Classifier: Development Status :: 5 - Production/Stable
Classifier: Environment :: Console
Classifier: Environment :: Web Environment
Classifier: Intended Audience :: Science/Research
Classifier: Intended Audience :: Developers
Classifier: License :: OSI Approved :: Apache Software License
Classifier: Programming Language :: Python :: 3 :: Only
Classifier: Programming Language :: Python :: 3.7
Classifier: Programming Language :: Python :: 3.8
Classifier: Programming Language :: Python :: 3.9
Classifier: Topic :: Scientific/Engineering
Classifier: Topic :: Scientific/Engineering :: Artificial Intelligence
Classifier: Topic :: Software Development
Classifier: Topic :: Software Development :: Libraries
Classifier: Topic :: Software Development :: Libraries :: Python Modules
Requires-Python: >=3.7
License-File: LICENSE
License-File: NOTICE
Requires-Dist: Flask >=2.1.0
Requires-Dist: Flask-Cors >=3.0.10
Requires-Dist: gunicorn >=21.2.0
Requires-Dist: itsdangerous >=1.1.0
Requires-Dist: Jinja2 >=2.10.1
Requires-Dist: MarkupSafe >=1.1.1
Requires-Dist: marshmallow >=3.10.0
Requires-Dist: numpy >=1.17.0
Requires-Dist: pillow >=6.2.0
Requires-Dist: protobuf <=3.20.1,>=3.13.0
Requires-Dist: psutil >=5.7.0
Requires-Dist: pyyaml >=5.3.1
Requires-Dist: scipy >=1.5.2
Requires-Dist: scikit-learn >=0.23.1
Requires-Dist: Werkzeug >2.1.0
Requires-Dist: pandas >=1.0.4
Requires-Dist: treelib >=1.6.1
Requires-Dist: grpcio >=1.39.0
Requires-Dist: XlsxWriter >=1.3.2
